primetools-0.0.2.dist-info/METADATA
primetools-0.0.2.dist-info/WHEEL
primetools/__init__.py
primetools/primetools.abi3.so
primetools-0.0.2.dist-info/RECORD
