Metadata-Version: 2.1
Name: primetools
Version: 0.0.2
Classifier: Programming Language :: Python :: 3
Classifier: License :: OSI Approved :: MIT License
Classifier: Development Status :: 2 - Pre-Alpha
Classifier: Operating System :: Microsoft :: Windows
Classifier: Operating System :: MacOS :: MacOS X
Classifier: Operating System :: POSIX :: Linux
Classifier: Programming Language :: Rust
Summary: Prime number tools written in rust.
Author-email: valkyrie_pilot <valk@randomairborne.dev>
Project-URL: Source, https://github.com/randomairborne/primetools
